{
  "users": [
    {
      "name": "Monkey D Luffy",
      "id": "DCVpfjJ-"
    },
    {
      "name": "Nguyễn Hải Sơn",
      "id": "G5Gi22Q-",
      "email": "nguyenhaison7@gmail.com",
      "password": "123456"
    },
    {
      "name": "Yasuo",
      "id": "xCxL3q3N"
    },
    {
      "name": "Naruto",
      "id": "uUexFnKJ"
    },
    {
      "name": "ACMCT HaiSon",
      "phone": "123456789",
      "id": "6A0NFygq"
    },
    {
      "name": "Gold D Roger",
      "phone": "000-000-000",
      "id": "wMb87Shz"
    }
  ]
}